Freebsd101Hacks/README.md
Freebsd101Hacks/__init__.py
Freebsd101Hacks/__main__.py
Freebsd101Hacks/file.epub
Freebsd101Hacks/index.html
Freebsd101Hacks/css/__init__.py
Freebsd101Hacks/css/annotations.css
Freebsd101Hacks/css/main.css
Freebsd101Hacks/css/normalize.css
Freebsd101Hacks/css/popup.css
Freebsd101Hacks/font/__init__.py
Freebsd101Hacks/font/fontello.eot
Freebsd101Hacks/font/fontello.svg
Freebsd101Hacks/font/fontello.ttf
Freebsd101Hacks/font/fontello.woff
Freebsd101Hacks/img/__init__.py
Freebsd101Hacks/img/annotator-glyph-sprite.png
Freebsd101Hacks/img/annotator-icon-sprite.png
Freebsd101Hacks/img/apple-touch-icon.png
Freebsd101Hacks/img/cancelfullscreen.png
Freebsd101Hacks/img/close.png
Freebsd101Hacks/img/fullscreen.png
Freebsd101Hacks/img/loader.gif
Freebsd101Hacks/img/menu-icon.png
Freebsd101Hacks/img/save.png
Freebsd101Hacks/img/saved.png
Freebsd101Hacks/img/settings-s.png
Freebsd101Hacks/img/settings.png
Freebsd101Hacks/img/star.png
Freebsd101Hacks/js/__init__.py
Freebsd101Hacks/js/epub.js
Freebsd101Hacks/js/epub.min.js
Freebsd101Hacks/js/epub.min.map
Freebsd101Hacks/js/hooks.min.js
Freebsd101Hacks/js/hooks.min.map
Freebsd101Hacks/js/reader.js
Freebsd101Hacks/js/reader.js.map
Freebsd101Hacks/js/reader.min.js
Freebsd101Hacks/js/reader.min.map
Freebsd101Hacks/js/hooks/__init__.py
Freebsd101Hacks/js/hooks/extensions/__init__.py
Freebsd101Hacks/js/hooks/extensions/highlight.js
Freebsd101Hacks/js/libs/__init__.py
Freebsd101Hacks/js/libs/jquery.min.js
Freebsd101Hacks/js/libs/localforage.min.js
Freebsd101Hacks/js/libs/screenfull.js
Freebsd101Hacks/js/libs/screenfull.min.js
Freebsd101Hacks/js/libs/zip.min.js
Freebsd101Hacks/js/plugins/__init__.py
Freebsd101Hacks/js/plugins/hypothesis.js
Freebsd101Hacks/js/plugins/search.js
freebsd_101_hacks-2024.3.3.0.dist-info/METADATA
freebsd_101_hacks-2024.3.3.0.dist-info/WHEEL
freebsd_101_hacks-2024.3.3.0.dist-info/entry_points.txt
freebsd_101_hacks-2024.3.3.0.dist-info/top_level.txt
freebsd_101_hacks-2024.3.3.0.dist-info/RECORD
